pytanque.cpython-39-darwin.so
pytanque-1.1.0.dist-info/LICENSE.txt
pytanque-1.1.0.dist-info/METADATA
pytanque-1.1.0.dist-info/WHEEL
pytanque-1.1.0.dist-info/top_level.txt
pytanque-1.1.0.dist-info/RECORD
