Metadata-Version: 2.1
Name: pytanque
Version: 1.1.0
Summary: petanque static python bindings
Home-page: https://github.com/quarkslab/arybo
Author: Adrien Guinet
Author-email: aguinet@quarkslab.com
License: BSD
Download-URL: https://github.com/quarkslab/arybo/releases
Keywords: symbolic computation canonicalization boolean-arithmetic expressions
Platform: UNKNOWN
Classifier: Development Status :: 5 - Production/Stable
Classifier: Intended Audience :: Science/Research
Classifier: Intended Audience :: Developers
Classifier: Topic :: Software Development :: Build Tools
Classifier: Topic :: Security
Classifier: Topic :: Scientific/Engineering
Classifier: License :: OSI Approved :: BSD License
Classifier: Programming Language :: Python :: 3
Classifier: Programming Language :: Python :: 3.5
Classifier: Programming Language :: Python :: 3.6
Classifier: Programming Language :: Python :: 3.7
Classifier: Programming Language :: Python :: 3.8
